pm_api_fetcher/__init__.py
pm_api_fetcher/polymarket.py
pm_api_fetcher-0.2.0.dist-info/METADATA
pm_api_fetcher-0.2.0.dist-info/WHEEL
pm_api_fetcher-0.2.0.dist-info/RECORD
