Metadata-Version: 2.4
Name: pm-api-fetcher
Version: 0.2.0
Summary: Helpers for exporting Polymarket series data
Author: pm-api-fetcher maintainers
License: MIT
Keywords: api,fetcher,polymarket,trading
Classifier: License :: OSI Approved :: MIT License
Classifier: Programming Language :: Python :: 3
Classifier: Programming Language :: Python :: 3.12
Classifier: Topic :: Software Development :: Libraries
Requires-Python: >=3.12
Requires-Dist: requests>=2.32.0
